knapsack_fractional.py
fractional_knapsack_jadencastelino-0.1.4.dist-info/METADATA
fractional_knapsack_jadencastelino-0.1.4.dist-info/WHEEL
fractional_knapsack_jadencastelino-0.1.4.dist-info/entry_points.txt
fractional_knapsack_jadencastelino-0.1.4.dist-info/top_level.txt
fractional_knapsack_jadencastelino-0.1.4.dist-info/RECORD
