Metadata-Version: 2.4
Name: fractional-knapsack-jadencastelino
Version: 0.1.4
Summary: Fractional Knapsack greedy solver
Author: Jaden Castelino
Requires-Python: >=3.8
